lit_saint/__init__.py
lit_saint/augmentations.py
lit_saint/config.py
lit_saint/datamodule.py
lit_saint/dataset.py
lit_saint/model.py
lit_saint/modules.py
lit_saint/trainer.py
lit_saint/version.py
lit_saint-0.4.1.dist-info/LICENSE
lit_saint-0.4.1.dist-info/METADATA
lit_saint-0.4.1.dist-info/WHEEL
lit_saint-0.4.1.dist-info/top_level.txt
lit_saint-0.4.1.dist-info/RECORD
